CalSciPy/__init__.py
CalSciPy/_calculations.py
CalSciPy/_files.py
CalSciPy/_helpers.py
CalSciPy/_user.py
CalSciPy/_validators.py
CalSciPy/_visual.py
CalSciPy/color_scheme.py
CalSciPy/console.mplstyle
CalSciPy/conversion.py
CalSciPy/io_tools.py
CalSciPy/main.mplstyle
CalSciPy/optogenetics.py
CalSciPy/publication.mplstyle
CalSciPy/version.py
CalSciPy/_backports/__init__.py
CalSciPy/_backports/kw_dataclasses.py
CalSciPy/_backports/pattern_matching.py
CalSciPy/bruker/__init__.py
CalSciPy/bruker/_helpers.py
CalSciPy/bruker/config.ini
CalSciPy/bruker/constants.py
CalSciPy/bruker/data.py
CalSciPy/bruker/experiments.py
CalSciPy/bruker/factories.py
CalSciPy/bruker/helpers.py
CalSciPy/bruker/meta/__init__.py
CalSciPy/bruker/meta/metafun.py
CalSciPy/bruker/meta/metaobj.py
CalSciPy/bruker/protocols/__init__.py
CalSciPy/bruker/protocols/_helpers.py
CalSciPy/bruker/protocols/mark_points.py
CalSciPy/bruker/xml/__init__.py
CalSciPy/bruker/xml/mapio.py
CalSciPy/bruker/xml/xmlobj.py
CalSciPy/bruker/xml/xml_mappings/5_5_64_600.json
CalSciPy/events/__init__.py
CalSciPy/events/events.py
CalSciPy/events/firing_rates.py
CalSciPy/images/__init__.py
CalSciPy/images/deinterlacing.py
CalSciPy/images/filters.py
CalSciPy/interactive/__init__.py
CalSciPy/interactive/image_comparison.py
CalSciPy/interactive/interactive.py
CalSciPy/optics/__init__.py
CalSciPy/organization/__init__.py
CalSciPy/organization/_logging_tools.py
CalSciPy/organization/experiment.py
CalSciPy/organization/files.py
CalSciPy/organization/imaging_experiment.py
CalSciPy/organization/prescreen_experiment.py
CalSciPy/organization/stimulation_experiment.py
CalSciPy/organization/subject.py
CalSciPy/roi_tools/__init__.py
CalSciPy/roi_tools/roi_tools.py
CalSciPy/roi_tools/suite2p_handler.py
CalSciPy/traces/__init__.py
CalSciPy/traces/baseline.py
CalSciPy/traces/smoothing.py
CalSciPy/traces/traces.py
CalSciPy-0.8.3.dist-info/LICENSE
CalSciPy-0.8.3.dist-info/METADATA
CalSciPy-0.8.3.dist-info/WHEEL
CalSciPy-0.8.3.dist-info/top_level.txt
CalSciPy-0.8.3.dist-info/RECORD
