Metadata-Version: 2.1
Name: CalSciPy
Version: 0.8.3
Summary: A toolbox for analyzing, designing, and visualizing multiphoton imaging & optogenetics experiments.
Author: Darik A. O'Neil
Maintainer: Darik A. O'Neil
License: MIT License
Project-URL: documentation, https://calscipy.readthedocs.io/en/latest/?badge=latest
Project-URL: repository, https://github.com/darikoneil/CalSciPy
Keywords: CalSciPy,Calcium Imaging
Classifier: Development Status :: 4 - Beta
Classifier: Programming Language :: Python
Classifier: Operating System :: Microsoft :: Windows
Classifier: Operating System :: POSIX
Classifier: Operating System :: Unix
Classifier: Programming Language :: Python :: 3.8
Classifier: Programming Language :: Python :: 3.9
Classifier: Programming Language :: Python :: 3.10
Requires-Python: <4,>=3.8
License-File: LICENSE
Requires-Dist: get-annotations
Requires-Dist: imageio
Requires-Dist: imageio-ffmpeg
Requires-Dist: importlib-metadata
Requires-Dist: ipykernel
Requires-Dist: ipython
Requires-Dist: joblib
Requires-Dist: json-tricks
Requires-Dist: matplotlib
Requires-Dist: memoization
Requires-Dist: numba
Requires-Dist: numpy
Requires-Dist: opencv-python
Requires-Dist: pandas
Requires-Dist: pillow <=9.4.0
Requires-Dist: PPVD
Requires-Dist: PyQt6
Requires-Dist: seaborn
Requires-Dist: scikit-learn
Requires-Dist: scipy
Requires-Dist: slmsuite
Requires-Dist: tqdm
Provides-Extra: development
Requires-Dist: build ; extra == 'development'
Requires-Dist: coverage[toml] ; extra == 'development'
Requires-Dist: coveralls ; extra == 'development'
Requires-Dist: flake8 ; extra == 'development'
Requires-Dist: flake8-annotations ; extra == 'development'
Requires-Dist: flake8-bugbear ; extra == 'development'
Requires-Dist: flake8-class-attributes-order ; extra == 'development'
Requires-Dist: flake8-comprehensions ; extra == 'development'
Requires-Dist: flake8-html ; extra == 'development'
Requires-Dist: flake8-unused-arguments ; extra == 'development'
Requires-Dist: pytest ; extra == 'development'
Requires-Dist: pytest-lazy-fixture ; extra == 'development'
Requires-Dist: pytest-sugar ; extra == 'development'
Requires-Dist: pytest-clarity ; extra == 'development'
Requires-Dist: toml ; extra == 'development'
Requires-Dist: tomli ; extra == 'development'
Requires-Dist: twine ; extra == 'development'
Provides-Extra: gpu
Requires-Dist: cupy ; extra == 'gpu'
Provides-Extra: prairielink
Requires-Dist: pywin32 ; extra == 'prairielink'
